epyk_web/__init__.py
epyk_web/_version.py
epyk_web/angular.py
epyk_web/apps.py
epyk_web/deno.py
epyk_web/jupyter.py
epyk_web/node.py
epyk_web/npm.py
epyk_web/react.py
epyk_web/svelte.py
epyk_web/templates.py
epyk_web/vue.py
epyk_web/components/__init__.py
epyk_web/components/angular/__init__.py
epyk_web/components/angular/bootstrap.py
epyk_web/components/angular/clarity.py
epyk_web/components/angular/materials.py
epyk_web/components/angular/primeng.py
epyk_web/components/angular/standards.py
epyk_web/components/angular/assets/__init__.py
epyk_web/components/angular/assets/asset.py
epyk_web/components/angular/assets/clr.py
epyk_web/components/angular/assets/mat.py
epyk_web/components/angular/assets/ngb.py
epyk_web/components/angular/assets/pr.py
epyk_web/components/react/__init__.py
epyk_web/components/react/fluentui.py
epyk_web/components/vue/__init__.py
epyk_web/components/widgets/IContainer.py
epyk_web/components/widgets/IProgress.py
epyk_web/components/widgets/ISelect.py
epyk_web/components/widgets/ISlider.py
epyk_web/components/widgets/IText.py
epyk_web/components/widgets/__init__.py
epyk_web-0.0.1.dist-info/LICENSE
epyk_web-0.0.1.dist-info/METADATA
epyk_web-0.0.1.dist-info/WHEEL
epyk_web-0.0.1.dist-info/top_level.txt
epyk_web-0.0.1.dist-info/RECORD
