Metadata-Version: 2.1
Name: epyk-web
Version: 0.0.1
Summary: Epyk bridge to popular web frameworks
Home-page: https://github.com/epykure/epyk-web
Author: epykure
Author-email: smith.pyotr@gmail.com
Project-URL: Documentation, http://www.epyk.io
Project-URL: Library, https://evergreen.segment.com/
Project-URL: Code, https://github.com/epykure/epyk-web
Classifier: Programming Language :: Python :: 3
Classifier: License :: OSI Approved :: GNU General Public License (GPL)
Classifier: Operating System :: OS Independent
Requires-Python: >=3.8
License-File: LICENSE
Requires-Dist: epyk
